nitrokey/__init__.py
nitrokey/_helpers.py
nitrokey/nk3/__init__.py
nitrokey/nk3/_bootloader.py
nitrokey/nk3/_device.py
nitrokey/nk3/secrets_app.py
nitrokey/nkpk.py
nitrokey/py.typed
nitrokey/trussed/__init__.py
nitrokey/trussed/_base.py
nitrokey/trussed/_bootloader/__init__.py
nitrokey/trussed/_bootloader/lpc55.py
nitrokey/trussed/_bootloader/lpc55_upload/README.md
nitrokey/trussed/_bootloader/lpc55_upload/__init__.py
nitrokey/trussed/_bootloader/lpc55_upload/crypto/__init__.py
nitrokey/trussed/_bootloader/lpc55_upload/crypto/certificate.py
nitrokey/trussed/_bootloader/lpc55_upload/crypto/hash.py
nitrokey/trussed/_bootloader/lpc55_upload/crypto/hmac.py
nitrokey/trussed/_bootloader/lpc55_upload/crypto/keys.py
nitrokey/trussed/_bootloader/lpc55_upload/crypto/symmetric.py
nitrokey/trussed/_bootloader/lpc55_upload/crypto/types.py
nitrokey/trussed/_bootloader/lpc55_upload/exceptions.py
nitrokey/trussed/_bootloader/lpc55_upload/mboot/__init__.py
nitrokey/trussed/_bootloader/lpc55_upload/mboot/commands.py
nitrokey/trussed/_bootloader/lpc55_upload/mboot/error_codes.py
nitrokey/trussed/_bootloader/lpc55_upload/mboot/exceptions.py
nitrokey/trussed/_bootloader/lpc55_upload/mboot/interfaces/__init__.py
nitrokey/trussed/_bootloader/lpc55_upload/mboot/interfaces/usb.py
nitrokey/trussed/_bootloader/lpc55_upload/mboot/mcuboot.py
nitrokey/trussed/_bootloader/lpc55_upload/mboot/memories.py
nitrokey/trussed/_bootloader/lpc55_upload/mboot/properties.py
nitrokey/trussed/_bootloader/lpc55_upload/mboot/protocol/__init__.py
nitrokey/trussed/_bootloader/lpc55_upload/mboot/protocol/base.py
nitrokey/trussed/_bootloader/lpc55_upload/mboot/protocol/bulk_protocol.py
nitrokey/trussed/_bootloader/lpc55_upload/sbfile/misc.py
nitrokey/trussed/_bootloader/lpc55_upload/sbfile/sb2/__init__.py
nitrokey/trussed/_bootloader/lpc55_upload/sbfile/sb2/commands.py
nitrokey/trussed/_bootloader/lpc55_upload/sbfile/sb2/headers.py
nitrokey/trussed/_bootloader/lpc55_upload/sbfile/sb2/images.py
nitrokey-0.4.2.dist-info/METADATA
nitrokey-0.4.2.dist-info/WHEEL
nitrokey-0.4.2.dist-info/licenses/LICENSES/Apache-2.0.txt
nitrokey-0.4.2.dist-info/licenses/LICENSES/MIT.txt
nitrokey-0.4.2.dist-info/RECORD
