Metadata-Version: 2.4
Name: nitrokey
Version: 0.4.2
Summary: Nitrokey Python SDK
License-Expression: Apache-2.0 OR MIT
License-File: LICENSES/Apache-2.0.txt
License-File: LICENSES/MIT.txt
Author: Nitrokey
Author-email: pypi@nitrokey.com
Requires-Python: >=3.10, <4
Classifier: Intended Audience :: Developers
Classifier: Programming Language :: Python :: 3
Classifier: Programming Language :: Python :: 3.10
Classifier: Programming Language :: Python :: 3.11
Classifier: Programming Language :: Python :: 3.12
Classifier: Programming Language :: Python :: 3.13
Classifier: Programming Language :: Python :: 3.14
Requires-Dist: crcmod (>=1.7,<2)
Requires-Dist: cryptography (>=41)
Requires-Dist: fido2 (>=1.1.2,<3)
Requires-Dist: hidapi (>=0.14,<0.15)
Requires-Dist: protobuf (>=5.26,<7)
Requires-Dist: pyserial (>=3.5,<4)
Requires-Dist: requests (>=2.16,<3)
Requires-Dist: semver (>=3,<4)
Requires-Dist: tlv8 (>=0.10,<0.11)
Project-URL: Repository, https://github.com/Nitrokey/nitrokey-sdk-py
